lou/__init__.py
lou-0.0.1.dist-info/LICENSE
lou-0.0.1.dist-info/METADATA
lou-0.0.1.dist-info/WHEEL
lou-0.0.1.dist-info/top_level.txt
lou-0.0.1.dist-info/RECORD
